datamind/__init__.py
datamind/agents/__init__.py
datamind/agents/auto_fix.py
datamind/agents/cleaning.py
datamind/agents/transformer.py
datamind/agents/validator.py
datamind/ai/__init__.py
datamind/ai/gemini.py
datamind/ai/groq_ai.py
datamind/cli/__init__.py
datamind/cli/interactive.py
datamind/cli/main.py
datamind/core/__init__.py
datamind/core/loader.py
datamind/dashboard/__init__.py
datamind/dashboard/charts.py
datamind/dashboard/generator.py
datamind_ai-0.1.8.dist-info/METADATA
datamind_ai-0.1.8.dist-info/WHEEL
datamind_ai-0.1.8.dist-info/entry_points.txt
datamind_ai-0.1.8.dist-info/top_level.txt
datamind_ai-0.1.8.dist-info/RECORD
