Metadata-Version: 2.4
Name: datamind-ai
Version: 0.1.8
Summary: AI-powered data analysis, cleaning, and dashboard generator CLI tool
Author-email: Saidjon Ravshanov <saidjonravshanov@example.com>
License: MIT
Keywords: ai,data-analysis,dashboard,gemini,groq,cli,data-cleaning,etl
Classifier: Development Status :: 3 - Alpha
Classifier: Environment :: Console
Classifier: Intended Audience :: Developers
Classifier: Intended Audience :: Science/Research
Classifier: License :: OSI Approved :: MIT License
Classifier: Programming Language :: Python :: 3
Classifier: Programming Language :: Python :: 3.9
Classifier: Programming Language :: Python :: 3.10
Classifier: Programming Language :: Python :: 3.11
Classifier: Programming Language :: Python :: 3.12
Classifier: Topic :: Scientific/Engineering :: Visualization
Requires-Python: >=3.9
Requires-Dist: typer>=0.9.0
Requires-Dist: rich>=13.0.0
Requires-Dist: pandas>=2.0.0
Requires-Dist: plotly>=5.18.0
Requires-Dist: google-generativeai>=0.3.0
Requires-Dist: groq>=0.4.0
Requires-Dist: jinja2>=3.1.0
Requires-Dist: openpyxl>=3.1.0
Requires-Dist: numpy>=1.24.0
Provides-Extra: dev
Requires-Dist: pytest>=7.0.0; extra == "dev"
Requires-Dist: black>=23.0.0; extra == "dev"
Requires-Dist: ruff>=0.1.0; extra == "dev"
